LED-blinky/blinky.v
module blinky(
  // ports
  input wire clock, 
  output wire light_on
);
  
  // this is executed every time the clock variable changes
  assign light_on = clock;

endmodule

LED-blinky/blinky_tb.v
module blinky_testbench();
  
  //  
  output reg clock;
  input wire light_on;

  // initial block is executed once
  initial begin
    // dump file and vars to use in gtkwave
    $dumpfile("test.vcd");
    $dumpvars(0, blinky_testbench);
    // initial value of clock
    clock = 1;
    #100 $finish;
  end
 
  // always block is executed over and over
  // must have a delay (#10) or else it will hang 
  always #1 clock = ~clock;

  // equivalent of putting wires into the blinky module
  blinky U_blinky(clock, light_on);

endmodule

LED-blinky/test.vcd
$date
	Tue Jul 27 10:29:28 2021
$end
$version
	Icarus Verilog
$end
$timescale
	1s
$end
$scope module blinky_testbench $end
$var wire 1 ! light_on $end
$var reg 1 " clock $end
$scope module U_blinky $end
$var wire 1 " clock $end
$var wire 1 ! light_on $end
$upscope $end
$upscope $end
$enddefinitions $end
#0
$dumpvars
1"
1!
$end
#1
0!
0"
#2
1!
1"
#3
0!
0"
#4
1!
1"
#5
0!
0"
#6
1!
1"
#7
0!
0"
#8
1!
1"
#9
0!
0"
#10
1!
1"
#11
0!
0"
#12
1!
1"
#13
0!
0"
#14
1!
1"
#15
0!
0"
#16
1!
1"
#17
0!
0"
#18
1!
1"
#19
0!
0"
#20
1!
1"
#21
0!
0"
#22
1!
1"
#23
0!
0"
#24
1!
1"
#25
0!
0"
#26
1!
1"
#27
0!
0"
#28
1!
1"
#29
0!
0"
#30
1!
1"
#31
0!
0"
#32
1!
1"
#33
0!
0"
#34
1!
1"
#35
0!
0"
#36
1!
1"
#37
0!
0"
#38
1!
1"
#39
0!
0"
#40
1!
1"
#41
0!
0"
#42
1!
1"
#43
0!
0"
#44
1!
1"
#45
0!
0"
#46
1!
1"
#47
0!
0"
#48
1!
1"
#49
0!
0"
#50
1!
1"
#51
0!
0"
#52
1!
1"
#53
0!
0"
#54
1!
1"
#55
0!
0"
#56
1!
1"
#57
0!
0"
#58
1!
1"
#59
0!
0"
#60
1!
1"
#61
0!
0"
#62
1!
1"
#63
0!
0"
#64
1!
1"
#65
0!
0"
#66
1!
1"
#67
0!
0"
#68
1!
1"
#69
0!
0"
#70
1!
1"
#71
0!
0"
#72
1!
1"
#73
0!
0"
#74
1!
1"
#75
0!
0"
#76
1!
1"
#77
0!
0"
#78
1!
1"
#79
0!
0"
#80
1!
1"
#81
0!
0"
#82
1!
1"
#83
0!
0"
#84
1!
1"
#85
0!
0"
#86
1!
1"
#87
0!
0"
#88
1!
1"
#89
0!
0"
#90
1!
1"
#91
0!
0"
#92
1!
1"
#93
0!
0"
#94
1!
1"
#95
0!
0"
#96
1!
1"
#97
0!
0"
#98
1!
1"
#99
0!
0"
#100
1!
1"
